cubejsclientasync/__init__.py
cubejsclientasync/client.py
cubejsclientasync/enums.py
cubejsclientasync/filters.py
cubejsclientasync/objects.py
cubejsclientasync/query.py
cubejsclientasync-0.1.0.dist-info/LICENSE.md
cubejsclientasync-0.1.0.dist-info/WHEEL
cubejsclientasync-0.1.0.dist-info/METADATA
cubejsclientasync-0.1.0.dist-info/RECORD
