Metadata-Version: 2.1
Name: cubejsclientasync
Version: 0.1.0
Summary: Async Python Cube.js client
Home-page: https://github.com/NarrativeScience/cubejs-client-async
License: BSD-3-Clause
Author: Jonathan Drake
Author-email: jdrake@narrativescience.com
Requires-Python: >=3.6.5,<4.0.0
Classifier: License :: OSI Approved :: BSD License
Classifier: Programming Language :: Python :: 3
Classifier: Programming Language :: Python :: 3.7
Classifier: Programming Language :: Python :: 3.8
Classifier: Programming Language :: Python :: 3.9
Requires-Dist: PyJWT (>=2.1.0,<3.0.0)
Requires-Dist: backoff (>=1.10.0,<2.0.0)
Requires-Dist: httpx (>=0.18.2,<0.19.0)
Project-URL: Repository, https://github.com/NarrativeScience/cubejs-client-async
